xue/__init__.py
xue/core.py
xue/markdown.py
xue/components/__init__.py
xue/components/button.py
xue/components/card.py
xue/components/chart.py
xue/components/checkbox.py
xue/components/data_table.py
xue/components/dropdown.py
xue/components/form.py
xue/components/input.py
xue/components/menubar.py
xue/components/model_config_row.py
xue/components/resizable.py
xue/components/select.py
xue/components/sheet.py
xue/components/sidebar.py
xue/icons/arrow-right-from-line.svg
xue/icons/chevron-left.svg
xue/icons/chevron-right.svg
xue/icons/database.svg
xue/icons/layout-dashboard.svg
xue/icons/scroll-text.svg
xue/icons/settings.svg
xue/icons/zap.svg
xue-0.0.34.dist-info/LICENSE
xue-0.0.34.dist-info/METADATA
xue-0.0.34.dist-info/WHEEL
xue-0.0.34.dist-info/top_level.txt
xue-0.0.34.dist-info/RECORD
