Metadata-Version: 2.1
Name: xue
Version: 0.0.34
Summary: A minimalist web front-end framework composed of HTMX and Python.
License-File: LICENSE
